imagefilter/1.py
imagefilter/__init__.py
imagefilter/cli.py
imagefilter/enhence.py
imagefilter/image.py
imagefilter/luts_adapter.py
imagefilter/mytypes.py
imagefilter/raw.py
imagefilter/raw_test.py
imagefilter/luts/astia.cube
imagefilter/luts/azrael.cube
imagefilter/luts/byers.cube
imagefilter/luts/cc.cube
imagefilter/luts/cn.cube
imagefilter/luts/eterna.cube
imagefilter/luts/land.cube
imagefilter/luts/lenox.cube
imagefilter/luts/nc.cube
imagefilter/luts/provia.cube
imagefilter/luts/sea.cube
imagefilter/luts/topaz.cube
imagefilter/luts/velvia.cube
imagefilter-0.1.dist-info/licenses/LICENSE.txt
imagefilter-0.1.dist-info/METADATA
imagefilter-0.1.dist-info/WHEEL
imagefilter-0.1.dist-info/entry_points.txt
imagefilter-0.1.dist-info/top_level.txt
imagefilter-0.1.dist-info/RECORD
