Metadata-Version: 2.4
Name: imagefilter
Version: 0.1
Summary: A tool to apply luts to image
Author-email: yuncliu <lyc1990@qq.com>
Maintainer-email: yuncliu <lyc1990@qq.com>
License: 木兰宽松许可证， 第2版
Keywords: image,setuptools,development
Classifier: Development Status :: 3 - Alpha
Classifier: Intended Audience :: Developers
Classifier: Topic :: Software Development :: Build Tools
Classifier: License :: OSI Approved :: MIT License
Classifier: Programming Language :: Python :: 3
Classifier: Programming Language :: Python :: 3.8
Classifier: Programming Language :: Python :: 3.9
Classifier: Programming Language :: Python :: 3.10
Classifier: Programming Language :: Python :: 3.11
Classifier: Programming Language :: Python :: 3.12
Classifier: Programming Language :: Python :: 3.13
Classifier: Programming Language :: Python :: 3 :: Only
Requires-Python: >=3.7
License-File: LICENSE.txt
Requires-Dist: pillow
Requires-Dist: pillow_lut
Requires-Dist: numpy
Requires-Dist: rawpy
Requires-Dist: piexif
Provides-Extra: dev
Requires-Dist: check-manifest; extra == "dev"
Provides-Extra: test
Requires-Dist: coverage; extra == "test"
Dynamic: license-file
